{
  "reponses": [
    {
      "id_reponse": "js_r001_a",
      "label": "let",
      "isCorrect": false,
      "identifiant_1": "js_quiz",
      "question_id": "js_q001"
    },
    {
      "id_reponse": "js_r001_b",
      "label": "var",
      "isCorrect": false,
      "identifiant_1": "js_quiz",
      "question_id": "js_q001"
    },
    {
      "id_reponse": "js_r001_c",
      "label": "const",
      "isCorrect": false,
      "identifiant_1": "js_quiz",
      "question_id": "js_q001"
    },
    {
      "id_reponse": "js_r001_d",
      "label": "All of the above",
      "isCorrect": true,
      "identifiant_1": "js_quiz",
      "question_id": "js_q001"
    },
    {
      "id_reponse": "js_r002_a",
      "label": "\"array\"",
      "isCorrect": false,
      "identifiant_1": "js_quiz",
      "question_id": "js_q002"
    },
    {
      "id_reponse": "js_r002_b",
      "label": "\"object\"",
      "isCorrect": true,
      "identifiant_1": "js_quiz",
      "question_id": "js_q002"
    },
    {
      "id_reponse": "js_r002_c",
      "label": "\"undefined\"",
      "isCorrect": false,
      "identifiant_1": "js_quiz",
      "question_id": "js_q002"
    },
    {
      "id_reponse": "js_r002_d",
      "label": "\"function\"",
      "isCorrect": false,
      "identifiant_1": "js_quiz",
      "question_id": "js_q002"
    },
    {
      "id_reponse": "js_r003_a",
      "label": "# This is a comment",
      "isCorrect": false,
      "identifiant_1": "js_quiz",
      "question_id": "js_q003"
    },
    {
      "id_reponse": "js_r003_b",
      "label": "/* This is a comment */",
      "isCorrect": false,
      "identifiant_1": "js_quiz",
      "question_id": "js_q003"
    },
    {
      "id_reponse": "js_r003_c",
      "label": "// This is a comment",
      "isCorrect": true,
      "identifiant_1": "js_quiz",
      "question_id": "js_q003"
    },
    {
      "id_reponse": "js_r003_d",
      "label": " This is a comment",
      "isCorrect": false,
      "identifiant_1": "js_quiz",
      "question_id": "js_q003"
    },
    {
      "id_reponse": "js_r004_a",
      "label": "true",
      "isCorrect": true,
      "identifiant_1": "js_quiz",
      "question_id": "js_q004"
    },
    {
      "id_reponse": "js_r004_b",
      "label": "false",
      "isCorrect": false,
      "identifiant_1": "js_quiz",
      "question_id": "js_q004"
    },
    {
      "id_reponse": "js_r004_c",
      "label": "undefined",
      "isCorrect": false,
      "identifiant_1": "js_quiz",
      "question_id": "js_q004"
    },
    {
      "id_reponse": "js_r004_d",
      "label": "NaN",
      "isCorrect": false,
      "identifiant_1": "js_quiz",
      "question_id": "js_q004"
    }
  ]
}